sacrerouge/__init__.py
sacrerouge/__main__.py
sacrerouge/arguments.py
sacrerouge/stats.py
sacrerouge/version.py
sacrerouge/commands/__init__.py
sacrerouge/commands/correlate.py
sacrerouge/commands/evaluate.py
sacrerouge/commands/metric_command.py
sacrerouge/commands/partial_conjunction_test.py
sacrerouge/commands/score.py
sacrerouge/commands/setup_dataset.py
sacrerouge/commands/setup_metric.py
sacrerouge/commands/stat_sig_test.py
sacrerouge/commands/subcommand.py
sacrerouge/common/__init__.py
sacrerouge/common/arguments.py
sacrerouge/common/checks.py
sacrerouge/common/from_params.py
sacrerouge/common/logging.py
sacrerouge/common/params.py
sacrerouge/common/registrable.py
sacrerouge/common/tempdir.py
sacrerouge/common/util.py
sacrerouge/common/testing/__init__.py
sacrerouge/common/testing/metric_test_cases.py
sacrerouge/common/testing/testing_metric.py
sacrerouge/common/testing/util.py
sacrerouge/data/__init__.py
sacrerouge/data/eval_instance.py
sacrerouge/data/fields.py
sacrerouge/data/jackknifers.py
sacrerouge/data/metrics.py
sacrerouge/data/metrics_dict.py
sacrerouge/data/pyramid.py
sacrerouge/data/types.py
sacrerouge/data/dataset_readers/__init__.py
sacrerouge/data/dataset_readers/dataset_reader.py
sacrerouge/data/dataset_readers/document_based.py
sacrerouge/data/dataset_readers/pyramid_based.py
sacrerouge/data/dataset_readers/reference_based.py
sacrerouge/data/dataset_readers/summary_only.py
sacrerouge/datasets/__init__.py
sacrerouge/datasets/bhandari2020/__init__.py
sacrerouge/datasets/bhandari2020/setup.py
sacrerouge/datasets/bhandari2020/subcommand.py
sacrerouge/datasets/chaganty2018/__init__.py
sacrerouge/datasets/chaganty2018/setup.py
sacrerouge/datasets/chaganty2018/subcommand.py
sacrerouge/datasets/duc_tac/__init__.py
sacrerouge/datasets/duc_tac/duc2001/__init__.py
sacrerouge/datasets/duc_tac/duc2001/subcommand.py
sacrerouge/datasets/duc_tac/duc2001/tasks.py
sacrerouge/datasets/duc_tac/duc2002/__init__.py
sacrerouge/datasets/duc_tac/duc2002/metrics.py
sacrerouge-0.2.5.dist-info/LICENSE
sacrerouge-0.2.5.dist-info/METADATA
sacrerouge-0.2.5.dist-info/WHEEL
sacrerouge-0.2.5.dist-info/entry_points.txt
sacrerouge-0.2.5.dist-info/top_level.txt
sacrerouge-0.2.5.dist-info/RECORD
