Metadata-Version: 2.1
Name: sacrerouge
Version: 0.2.5
Summary: An open-source library for summarization evaluation metrics
Home-page: https://github.com/danieldeutsch/sacrerouge
Author: Daniel Deutsch
License: UNKNOWN
Platform: UNKNOWN
Requires-Python: >=3.6
License-File: LICENSE
Requires-Dist: googledrivedownloader
Requires-Dist: jsons
Requires-Dist: lxml
Requires-Dist: matplotlib
Requires-Dist: nltk
Requires-Dist: numpy
Requires-Dist: overrides (==3.1.0)
Requires-Dist: pytest
Requires-Dist: repro (==0.1.1)
Requires-Dist: requests
Requires-Dist: scipy (>=1.5.2)
Requires-Dist: sacrebleu (==2.0.0)
